engagelab/__init__.py
engagelab-0.0.1.dist-info/METADATA
engagelab-0.0.1.dist-info/WHEEL
engagelab-0.0.1.dist-info/top_level.txt
engagelab-0.0.1.dist-info/RECORD
